packman/__init__.py
packman/__main__.py
packman/anm/__init__.py
packman/anm/anm.py
packman/anm/hd_anm.py
packman/apps/__init__.py
packman/apps/calculate_entropy.py
packman/apps/dci.py
packman/apps/hdanm.py
packman/apps/predict_hinge.py
packman/bin/GUI.py
packman/bin/PACKMAN.py
packman/bin/__init__.py
packman/bin/logo.ico
packman/constants/Constants.py
packman/constants/__init__.py
packman/entropy/__init__.py
packman/entropy/entropy.py
packman/geometry/__init__.py
packman/geometry/geometry.py
packman/gnm/__init__.py
packman/gnm/gnm.py
packman/molecule/__init__.py
packman/molecule/annotations.py
packman/molecule/atom.py
packman/molecule/bond.py
packman/molecule/chain.py
packman/molecule/hetmol.py
packman/molecule/model.py
packman/molecule/molecule.py
packman/molecule/protein.py
packman/molecule/residue.py
packman/tests/__init__.py
packman/tests/anm/__init__.py
packman/tests/anm/test_anm.py
packman/tests/data/1prw.hng
packman/tests/data/1prw.pdb
packman/tests/data/4hla.cif
packman/tests/data/4hla.hng
packman/tests/data/__init__.py
packman/tests/entropy/__init__.py
packman/tests/entropy/test_entropy.py
packman/tests/molecule/__init__.py
packman/tests/molecule/test_molecule.py
packman/utilities/__init__.py
packman/utilities/utilities.py
py_packman-1.4.13.dist-info/LICENSE
py_packman-1.4.13.dist-info/METADATA
py_packman-1.4.13.dist-info/WHEEL
py_packman-1.4.13.dist-info/entry_points.txt
py_packman-1.4.13.dist-info/top_level.txt
py_packman-1.4.13.dist-info/RECORD
